ivobject/__init__.py
ivobject/decorator.py
ivobject/exceptions.py
ivobject/ivobject.py
IVObject-1.0.2.dist-info/LICENSE
IVObject-1.0.2.dist-info/METADATA
IVObject-1.0.2.dist-info/WHEEL
IVObject-1.0.2.dist-info/top_level.txt
IVObject-1.0.2.dist-info/RECORD
